deutschland/studiensuche/__init__.py
deutschland/studiensuche/api/__init__.py
deutschland/studiensuche/api/default_api.py
deutschland/studiensuche/api_client.py
deutschland/studiensuche/apis/__init__.py
deutschland/studiensuche/configuration.py
deutschland/studiensuche/exceptions.py
deutschland/studiensuche/model/__init__.py
deutschland/studiensuche/model/response.py
deutschland/studiensuche/model/response_auswahl.py
deutschland/studiensuche/model/response_facetten.py
deutschland/studiensuche/model/response_items.py
deutschland/studiensuche/model/response_studienangebot.py
deutschland/studiensuche/model/response_studienangebot_abschlussgrad.py
deutschland/studiensuche/model/response_studienangebot_hochschulart.py
deutschland/studiensuche/model/response_studienangebot_region.py
deutschland/studiensuche/model/response_studienangebot_studienanbieter.py
deutschland/studiensuche/model/response_studienangebot_studienanbieter_logo.py
deutschland/studiensuche/model/response_studienangebot_studienform.py
deutschland/studiensuche/model/response_studienangebot_studienmodelle.py
deutschland/studiensuche/model/response_studienangebot_studienort.py
deutschland/studiensuche/model/response_studienangebot_studienort_location.py
deutschland/studiensuche/model/response_studienangebot_studientyp.py
deutschland/studiensuche/model_utils.py
deutschland/studiensuche/models/__init__.py
deutschland/studiensuche/rest.py
de_studiensuche-0.1.0.dist-info/WHEEL
de_studiensuche-0.1.0.dist-info/METADATA
de_studiensuche-0.1.0.dist-info/RECORD
